pure_sql/__init__.py
pure_sql/exceptions.py
pure_sql/patterns.py
pure_sql/pure_sql.py
pure_sql/query_loader.py
pure_sql/types.py
pure_sql-0.2.0.dist-info/LICENSE
pure_sql-0.2.0.dist-info/METADATA
pure_sql-0.2.0.dist-info/WHEEL
pure_sql-0.2.0.dist-info/top_level.txt
pure_sql-0.2.0.dist-info/RECORD
