Metadata-Version: 2.1
Name: pure-sql
Version: 0.2.0
Summary: Raw SQL in Python
Home-page: https://github.com/sysid/pure-sql
Author: sysid
Author-email: sysid@gmx.de
License: BSD 3-Clause License
Classifier: Development Status :: 3 - Alpha
Classifier: Programming Language :: Python :: 3
Classifier: License :: OSI Approved :: BSD License
Classifier: Operating System :: OS Independent
Requires-Python: >=3.8
License-File: LICENSE
Requires-Dist: click
Requires-Dist: markt
